pyfortiapi.py
PyFortiAPI-0.3.0.dist-info/LICENSE.txt
PyFortiAPI-0.3.0.dist-info/METADATA
PyFortiAPI-0.3.0.dist-info/WHEEL
PyFortiAPI-0.3.0.dist-info/top_level.txt
PyFortiAPI-0.3.0.dist-info/RECORD
